wrarc/.DS_Store
wrarc/bulk.json
wrarc/bulk.yaml
wrarc/cmd/__init__.py
wrarc/cmd/close.py
wrarc/cmd/create.py
wrarc/cmd/lookup.py
wrarc/cmd/medit.py
wrarc/cmd/stats.py
wrarc/helpers.py
wrarc/main.py
wrarc/main.spec
wrarc/phab_wrapper.py
wrarc/presenter.py
wrarc/transaction_builder.py
wrarc/util.py
wrarc/validation.py
wrarc-0.1.1.dist-info/entry_points.txt
wrarc-0.1.1.dist-info/WHEEL
wrarc-0.1.1.dist-info/METADATA
wrarc-0.1.1.dist-info/RECORD
